gqxls/__init__.py
gqxls/convert/__init__.py
gqxls/convert/_pdf.py
gqxls/convert/_unit.py
gqxls/information/__init__.py
gqxls/information/_gain.py
gqxls/network/__init__.py
gqxls/network/_download.py
gqxls/path/__init__.py
gqxls/path/_paths.py
gqxls/system/__init__.py
gqxls/system/_info.py
gqxls-0.0.12.dist-info/LICENSE
gqxls-0.0.12.dist-info/METADATA
gqxls-0.0.12.dist-info/WHEEL
gqxls-0.0.12.dist-info/top_level.txt
gqxls-0.0.12.dist-info/RECORD
