Metadata-Version: 2.1
Name: gqxls
Version: 0.0.12
Summary: Consolidation package for daily use
Author: S Liao
Author-email: shunliaopetroleum@163.com
License: GNU General Public License v3.0
Project-URL: Source, https://github.com/891011well/gqxls
Project-URL: Bug Tracker, https://github.com/891011well/gqxls/issues
Keywords: python,gqxls
Platform: any
Classifier: License :: OSI Approved :: GNU General Public License v3 (GPLv3)
Classifier: Programming Language :: Python :: 3.11
Requires-Python: >=3.6
License-File: LICENSE
Requires-Dist: pillow<=10.4.0
Requires-Dist: pymupdf<=1.24.11
Requires-Dist: urllib3<=2.2.2
Requires-Dist: bs4<=4.12.3
